pen/__init__.py
pen/__main__.py
pen/_version.py
pen/cli.py
pen/commands.py
pen/config.py
pen/entry.py
pen/exceptions.py
pen/gitsync.py
pen/hookspec.py
pen/journal.py
pen/parsing.py
pen/py.typed
pen/serializing.py
pen/utils.py
pen-0.1.0a4.dist-info/LICENSE
pen-0.1.0a4.dist-info/METADATA
pen-0.1.0a4.dist-info/WHEEL
pen-0.1.0a4.dist-info/entry_points.txt
pen-0.1.0a4.dist-info/top_level.txt
pen-0.1.0a4.dist-info/RECORD
