Metadata-Version: 2.1
Name: pen
Version: 0.1.0a4
Summary: Simple cli that creates and manages text-based journals
Home-page: http://github.com/pspeter/pen
Author: Peter Schmidbauer
Author-email: peter.schmidb@gmail.com
License: MIT
Download-URL: http://pypi.python.org/pypi/pen
Project-URL: Source, http://github.com/pspeter/pen
Project-URL: Tracker, http://github.com/pspeter/pen/issues
Keywords: pen,diary,journal,note-taking,daybook,cli
Platform: UNKNOWN
Classifier: Development Status :: 3 - Alpha
Classifier: License :: OSI Approved :: MIT License
Classifier: Environment :: Console
Classifier: Operating System :: MacOS :: MacOS X
Classifier: Operating System :: POSIX :: Linux
Classifier: Programming Language :: Python :: 3 :: Only
Classifier: Programming Language :: Python :: 3.6
Classifier: Programming Language :: Python :: 3.7
Classifier: Programming Language :: Python :: 3.8
Classifier: Topic :: Utilities
Classifier: Typing :: Typed
Requires-Dist: pluggy
Requires-Dist: dateparser
Requires-Dist: tomlkit
